lab01/exp2/exp2.v
module exp2(
	input  [7:0] X,
	input  en,
	output reg valid,
	output [2:0] Z, 
	output [6:0] F,
	output [7:0] AN,
	output DP
	);

	reg [3:0] Y;
    always @(*)
		if (en) begin
			casez(X)
				8'b1???????: begin Y=4'b0111; valid=1'b1; end
				8'b01??????: begin Y=4'b0110; valid=1'b1; end
				8'b001?????: begin Y=4'b0101; valid=1'b1; end
				8'b0001????: begin Y=4'b0100; valid=1'b1; end
				8'b00001???: begin Y=4'b0011; valid=1'b1; end
				8'b000001??: begin Y=4'b0010; valid=1'b1; end
				8'b0000001?: begin Y=4'b0001; valid=1'b1; end
				8'b00000001: begin Y=4'b0000; valid=1'b1; end
				default: begin Y=4'b1111; valid=1'b0; end
			endcase
		end
		else begin
			Y=4'b1111; valid=1'b0;
		end
	bcd7seg b1(Y,F);
	assign Z[2]=Y[2]&valid;
	assign Z[1]=Y[1]&valid;
	assign Z[0]=Y[0]&valid;
	assign AN=8'b11111110;
	assign DP=1'b1;

endmodule

module bcd7seg(
    input  [3:0] b,
    output reg [6:0] h
);
    always @(*) begin
        case (b)
            4'd0:    h = 7'b1000000;
            4'd1:    h = 7'b1111001;
            4'd2:    h = 7'b0100100;
            4'd3:    h = 7'b0110000;
            4'd4:    h = 7'b0011001;
            4'd5:    h = 7'b0010010;
            4'd6:    h = 7'b0000010;
            4'd7:    h = 7'b1111000;
			4'd8:    h = 7'b0000000;
			4'd9:	 h = 7'b0010000;
            default: h = 7'b1111111;
        endcase
    end
endmodule

lab01/exp2/sim/tb.v
`timescale 1ns / 1ps
module tb_top;
    reg  [7:0] X;
    reg        en;
    wire       valid;
    wire [2:0] Z;
    wire [6:0] F;
    wire [7:0] AN;
    wire       DP;

    exp2 uut (
        .X(X), .en(en), .valid(valid), .Z(Z),
        .F(F), .AN(AN), .DP(DP)
    );

    initial begin
        $dumpfile("build/top.vcd");
        $dumpvars(0, tb_top);
    end

    initial begin
        en = 1'b1;
        X = 8'b10000000; #100;   // 最高优先级 -> Y=111
        X = 8'b01000000; #100;   // -> 110
        X = 8'b00100000; #100;   // -> 101
        X = 8'b00010000; #100;   // -> 100
        X = 8'b00001000; #100;   // -> 011
        X = 8'b00000100; #100;   // -> 010
        X = 8'b00000010; #100;   // -> 001
        X = 8'b00000001; #100;   // -> 000
        X = 8'b00100100; #100;   // 多个 1，最高优先 -> 101
        X = 8'b00000000; #100;   // 全 0 -> valid=0
        en = 1'b0; X = 8'b10000000; #100;  // 未使能 -> valid=0
        #100; $finish;
    end
endmodule

lab01/exp2/build/top.vcd
$date
   Tue Sep  1 15:18:47 2026
$end
$version
  2020.2
$end
$timescale
  1ps
$end
$scope module tb_top $end
$var reg 8 ! X [7:0] $end
$var reg 1 " en $end
$var wire 1 # valid $end
$var wire 3 $ Z [2:0] $end
$var wire 7 % F [6:0] $end
$var wire 8 & AN [7:0] $end
$var wire 1 ' DP $end
$scope module uut $end
$var wire 8 ( X [7:0] $end
$var wire 1 ) en $end
$var reg 1 * valid $end
$var wire 3 $ Z [2:0] $end
$var wire 7 % F [6:0] $end
$var wire 8 & AN [7:0] $end
$var wire 1 ' DP $end
$var reg 4 + Y [3:0] $end
$scope module b1 $end
$var wire 4 , b [3:0] $end
$var reg 7 - h [6:0] $end
$upscope $end
$upscope $end
$upscope $end
$enddefinitions $end
#0
$dumpvars
b10000000 !
1"
1#
b111 $
b1111000 %
b11111110 &
1'
b10000000 (
1)
1*
b111 +
b111 ,
b1111000 -
$end
#100000
b1000000 !
b110 $
b10 %
b1000000 (
1*
b110 +
b110 ,
b10 -
#200000
b100000 !
b101 $
b10010 %
b100000 (
1*
b101 +
b101 ,
b10010 -
#300000
b10000 !
b100 $
b11001 %
b10000 (
1*
b100 +
b100 ,
b11001 -
#400000
b1000 !
b11 $
b110000 %
b1000 (
1*
b11 +
b11 ,
b110000 -
#500000
b100 !
b10 $
b100100 %
b100 (
1*
b10 +
b10 ,
b100100 -
#600000
b10 !
b1 $
b1111001 %
b10 (
1*
b1 +
b1 ,
b1111001 -
#700000
b1 !
b0 $
b1000000 %
b1 (
1*
b0 +
b0 ,
b1000000 -
#800000
b100100 !
b101 $
b10010 %
b100100 (
1*
b101 +
b101 ,
b10010 -
#900000
b0 !
0#
b0 $
b1111111 %
b0 (
0*
b1111 +
b1111 ,
b1111111 -
#1000000
b10000000 !
0"
b10000000 (
0)
0*
b1111 +
